redesbayesianas/__init__.py
redesbayesianas-0.1.1.dist-info/licenses/LICENSE
redesbayesianas-0.1.1.dist-info/METADATA
redesbayesianas-0.1.1.dist-info/WHEEL
redesbayesianas-0.1.1.dist-info/top_level.txt
redesbayesianas-0.1.1.dist-info/RECORD
