Metadata-Version: 2.4
Name: redesbayesianas
Version: 0.1.1
Summary: Redes Bayesianas
Home-page: https://github.com/pshiguihara/phd
Author: Pedro Shiguihara
Author-email: p.shiguihara@gmail.com
License: MIT
Classifier: Programming Language :: Python :: 3
Classifier: License :: OSI Approved :: MIT License
Classifier: Operating System :: OS Independent
Requires-Python: >=3.10
License-File: LICENSE
Dynamic: license-file
